yt_cli_dl/__init__.py
yt_cli_dl/cli.py
yt_cli_dl/version.py
yt_cli_dl-1.0.0.dist-info/LICENSE
yt_cli_dl-1.0.0.dist-info/METADATA
yt_cli_dl-1.0.0.dist-info/WHEEL
yt_cli_dl-1.0.0.dist-info/entry_points.txt
yt_cli_dl-1.0.0.dist-info/top_level.txt
yt_cli_dl-1.0.0.dist-info/RECORD
