Metadata-Version: 2.1
Name: yt-cli-dl
Version: 1.0.0
Summary: A YouTube video and playlist downloader command-line interface (CLI) tool
Home-page: https://github.com/hendurhance/yt-downloader-cli
Author: Endurance
Author-email: hendurhance.dev@gmail.com
License: MIT License
Classifier: Programming Language :: Python :: 3
Classifier: License :: OSI Approved :: MIT License
Classifier: Operating System :: OS Independent
Requires-Python: >=3.6
License-File: LICENSE
